{
    "calendar": [
        {
            "round": 1,
            "name": "Australia",
            "start": "2025-03-14",
            "end": "2025-03-16",
            "location": "Melbourne",
            "coordinates": {
                "lat": -37.8497,
                "lon": 144.968
            },
            "description": {
                "country": "Australia",
                "location": "Melbourne, Victoria",
                "opened": 1996,
                "usedSince": 1996,
                "length": "5.279 km",
                "direction": "clockwise",
                "lapRecord": "1:20.235 (Charles Leclerc, Ferrari, 2022)"
            },
            "sprint": false,
            "sessions": {
                "practice1": "2025-03-14T02:30:00Z",
                "practice2": "2025-03-14T06:00:00Z",
                "practice3": "2025-03-15T02:30:00Z",
                "quali": "2025-03-15T06:00:00Z",
                "qualiResults": {
                    "1": "Lando Norris",
                    "2": "Oscar Piastri",
                    "3": "Max Verstappen",
                    "4": "George Russell",
                    "5": "Yuki Tsunoda",
                    "6": "Alex Albon",
                    "7": "Charles Leclerc",
                    "8": "Lewis Hamilton",
                    "9": "Pierre Gasly",
                    "10": "Carlos Sainz",
                    "11": "Esteban Ocon",
                    "12": "Liam Lawson",
                    "13": "Oliver Bearman",
                    "14": "Kimi Antonelli",
                    "15": "Lance Stroll",
                    "16": "Fernando Alonso",
                    "17": "Isack Hadjar",
                    "18": "Jack Doohan",
                    "19": "Nico Hulkenberg",
                    "20": "Gabriel Bortoleto"
                },
                "race": "2025-03-16T05:00:00Z",
                "raceResults": {
                    "1": "Lando Norris",
                    "2": "Max Verstappen",
                    "3": "George Russell",
                    "4": "Kimi Antonelli",
                    "5": "Alex Albon",
                    "6": "Lance Stroll",
                    "7": "Nico Hulkenberg",
                    "8": "Charles Leclerc",
                    "9": "Oscar Piastri",
                    "10": "Lewis Hamilton",
                    "11": "Pierre Gasly",
                    "12": "Yuki Tsunoda",
                    "13": "Esteban Ocon",
                    "14": "Oliver Bearman",
                    "DNF": ["Liam Lawson", "Gabriel Bortoleto", "Fernando Alonso", "Carlos Sainz", "Jack Doohan", "Isack Hadjar"]
                }
            }
        },
    {
        "round": 2,
        "name": "China",
        "start": "2025-03-21",
        "end": "2025-03-23",
        "location": "Shanghai",
        "coordinates": {
            "lat": 31.3389,
            "lon": 121.2204
        },
        "description": {
            "country": "China",
            "location": "Shanghai",
            "opened": 2004,
            "usedSince": 2004,
            "length": "5.451 km",
            "direction": "clockwise",
            "lapRecord": "1:32.238 (Michael Schumacher, Ferrari, 2004)"
        },
        "sprint": true,
        "sessions": {
            "practice1": "2025-03-21T03:30:00Z",
            "sprintQuali": "2025-03-21T07:30:00Z",
            "sprintQualiResults": {
                "1": "Lewis Hamilton",
                "2": "Max Verstappen",
                "3": "Oscar Piastri",
                "4": "George Russell",
                "5": "Charles Leclerc",
                "6": "Lando Norris",
                "7": "Yuki Tsunoda",
                "8": "Alex Albon",
                "9": "Pierre Gasly",
                "10": "Carlos Sainz",
                "11": "Esteban Ocon",
                "12": "Kimi Antonelli",
                "13": "Oliver Bearman",
                "14": "Liam Lawson",
                "15": "Lance Stroll",
                "16": "Fernando Alonso",
                "17": "Isack Hadjar",
                "18": "Jack Doohan",
                "19": "Nico Hulkenberg",
                "20": "Gabriel Bortoleto"
            },
            "sprint": "2025-03-22T04:00:00Z",
            "sprintRace": {
                "1": "Lewis Hamilton",
                "2": "Oscar Piastri",
                "3": "Max Verstappen",
                "4": "George Russell",
                "5": "Charles Leclerc",
                "6": "Yuki Tsunoda",
                "7": "Kimi Antonelli",
                "8": "Lando Norris",
                "9": "Lance Stroll",
                "10": "Fernando Alonso",
                "11": "Alex Albon",
                "12": "Pierre Gasly",
                "13": "Isack Hadjar",
                "14": "Liam Lawson",
                "15": "Oliver Bearman",
                "16": "Esteban Ocon",
                "17": "Carlos Sainz",
                "18": "Gabriel Bortoleto",
                "19": "Nico Hulkenberg",
                "20": "Jack Doohan"
            },
            "quali": "2025-03-22T08:00:00Z",
            "qualiResults": {
                "1": "Oscar Piastri",
                "2": "George Russell",
                "3": "Lando Norris",
                "4": "Max Verstappen",
                "5": "Lewis Hamilton",
                "6": "Charles Leclerc",
                "7": "Yuki Tsunoda",
                "8": "Alex Albon",
                "9": "Pierre Gasly",
                "10": "Carlos Sainz",
                "11": "Esteban Ocon",
                "12": "Kimi Antonelli",
                "13": "Oliver Bearman",
                "14": "Liam Lawson",
                "15": "Lance Stroll",
                "16": "Fernando Alonso",
                "17": "Isack Hadjar",
                "18": "Jack Doohan",
                "19": "Nico Hulkenberg",
                "20": "Gabriel Bortoleto"
            },
            "race": "2025-03-23T07:00:00Z",
            "raceResults": {
                "1": "Oscar Piastri",
                "2": "Lando Norris",
                "3": "George Russell",
                "4": "Max Verstappen",
                "5": "Esteban Ocon",
                "6": "Kimi Antonelli",
                "7": "Alex Albon",
                "8": "Oliver Bearman",
                "9": "Lance Stroll",
                "10": "Carlos Sainz",
                "11": "Isack Hadjar",
                "12": "Liam Lawson",
                "13": "Jack Doohan",
                "14": "Gabriel Bortoleto",
                "15": "Nico Hulkenberg",
                "16": "Yuki Tsunoda",
                "DNF": ["Fernando Alonso"],
                "DQ": ["Charles Leclerc", "Lewis Hamilton", "Pierre Gasly"]
            }
        }
    },
    {
        "round": 3,
        "name": "Japan",
        "start": "2025-04-04",
        "end": "2025-04-06",
        "location": "Suzuka",
        "coordinates": {
            "lat": 34.8431,
            "lon": 136.5411
        },
        "description": {
            "country": "Japan",
            "location": "Mie Prefecture",
            "opened": 1962,
            "usedSince": 1987,
            "length": "5.807 km",
            "direction": "clockwise, figure-eight",
            "lapRecord": "1:27.064 (Sebastian Vettel, Ferrari, 2019)"
        },
        "sprint": false,
        "sessions": {
            "practice1": "2025-04-04T02:30:00Z",
            "practice2": "2025-04-04T06:00:00Z",
            "practice3": "2025-04-05T02:30:00Z",
            "quali": "2025-04-05T06:00:00Z",
            "qualiResults": {
                "1": "Max Verstappen",
                "2": "Lando Norris",
                "3": "Oscar Piastri",
                "4": "Charles Leclerc",
                "5": "George Russell",
                "6": "Kimi Antonelli",
                "7": "Isack Hadjar",
                "8": "Lewis Hamilton",
                "9": "Alex Albon",
                "10": "Oliver Bearman",
                "11": "Pierre Gasly",
                "12": "Carlos Sainz",
                "13": "Fernando Alonso",
                "14": "Liam Lawson",
                "15": "Yuki Tsunoda",
                "16": "Nico Hulkenberg",
                "17": "Gabriel Bortoleto",
                "18": "Esteban Ocon",
                "19": "Jack Doohan",
                "20": "Lance Stroll"
            },
            "race": "2025-04-06T05:00:00Z",
            "raceResults": {
                "1": "Max Verstappen",
                "2": "Lando Norris",
                "3": "Oscar Piastri",
                "4": "Charles Leclerc",
                "5": "George Russell",
                "6": "Kimi Antonelli",
                "7": "Lewis Hamilton",
                "8": "Isack Hadjar",
                "9": "Alex Albon",
                "10": "Oliver Bearman",
                "11": "Fernando Alonso",
                "12": "Yuki Tsunoda",
                "13": "Pierre Gasly",
                "14": "Carlos Sainz",
                "15": "Jack Doohan",
                "16": "Nico Hulkenberg",
                "17": "Liam Lawson",
                "18": "Esteban Ocon",
                "19": "Gabriel Bortoleto",
                "20": "Lance Stroll"
    }
        }
    },
    {
        "round": 4,
        "name": "Bahrain",
        "start": "2025-04-11",
        "end": "2025-04-13",
        "location": "Sakhir",
        "coordinates": {
            "lat": 26.0325,
            "lon": 50.5106
        },
        "description": {
            "country": "Bahrain",
            "location": "Sakhir",
            "opened": 2004,
            "usedSince": 2004,
            "length": "5.412 km",
            "direction": "clockwise",
            "lapRecord": "1:31.447 (Pedro de la Rosa, McLaren, 2005)"
        },
        "sprint": false,
        "sessions": {
        "practice1": "2025-04-11T11:30:00Z",
        "practice2": "2025-04-11T15:00:00Z",
        "practice3": "2025-04-12T12:30:00Z",
        "quali": "2025-04-12T16:00:00Z",
        "qualiResults": {
                "1": "Oscar Piastri",
                "2": "George Russell",
                "3": "Charles Leclerc",
                "4": "Kimi Antonelli",
                "5": "Pierre Galsy",
                "6": "Lando Norris",
                "7": "Max Verstappen",
                "8": "Carlos Sainz",
                "9": "Lewis Hamilton",
                "10": "Yuki Tsunoda",
                "11": "Jack Doohan",
                "12": "Isack Hadjar",
                "13": "Fernando Alonso",
                "14": "Esteban Ocon",
                "15": "Alex Albon",
                "16": "Nico Hulkenberg",
                "17": "Liam Lawson",
                "18": "Gabriel Bortoleto",
                "19": "Lance Stroll",
                "20": "Oliver Bearman"
            },
        "race": "2025-04-13T15:00:00Z"
}
    },
    {
        "round": 5,
        "name": "Saudi Arabia",
        "start": "2025-04-18",
        "end": "2025-04-20",
        "location": "Jeddah",
        "coordinates": {
            "lat": 21.6319,
            "lon": 39.1044
        },
        "description": {
            "country": "Saudi Arabia",
            "location": "Jeddah",
            "opened": 2021,
            "usedSince": 2021,
            "length": "6.174 km",
            "direction": "counterclockwise",
            "lapRecord": "1:30.734 (Lewis Hamilton, Mercedes, 2021)"
        },
        "sprint": false,
        "sessions": {
        "practice1": "2025-04-18T12:30:00Z",
        "practice2": "2025-04-18T16:00:00Z",
        "practice3": "2025-04-19T12:30:00Z",
        "quali": "2025-04-19T16:00:00Z",
        "race": "2025-04-20T16:00:00Z"
}
    },
    {
        "round": 6,
        "name": "Miami",
        "start": "2025-05-02",
        "end": "2025-05-04",
        "location": "Miami",
        "coordinates": {
            "lat": 25.9581,
            "lon": -80.2389
        },
        "description": {
            "country": "United States",
            "location": "Miami, Florida",
            "opened": 2022,
            "usedSince": 2022,
            "length": "5.412 km",
            "direction": "counterclockwise",
            "lapRecord": "1:29.708 (Max Verstappen, Red Bull, 2023)"
        },
        "sprint": true,
        "sessions": {
        "practice1": "2025-05-02T14:30:00Z",
        "sprintQuali": "2025-05-02T18:30:00Z",
        "sprint": "2025-05-03T14:00:00Z",
        "quali": "2025-05-03T18:00:00Z",
        "race": "2025-05-04T18:00:00Z"
}
    },
    {
        "round": 7,
        "name": "Emilia-Romagna",
        "start": "2025-05-16",
        "end": "2025-05-18",
        "location": "Imola",
        "coordinates": {
            "lat": 44.3439,
            "lon": 11.7167
        },
        "description": {
            "country": "Italy",
            "location": "Imola, Emilia-Romagna",
            "opened": 1953,
            "usedSince": 1980,
            "length": "4.909 km",
            "direction": "counterclockwise",
            "lapRecord": "1:15.484 (Lewis Hamilton, Mercedes, 2020)"
        },
        "sprint": false,
        "sessions": {
        "practice1": "2025-05-16T11:30:00Z",
        "practice2": "2025-05-16T15:00:00Z",
        "practice3": "2025-05-17T10:30:00Z",
        "quali": "2025-05-17T14:00:00Z",
        "race": "2025-05-18T13:00:00Z"
}
    },
    {
        "round": 8,
        "name": "Monaco",
        "start": "2025-05-23",
        "end": "2025-05-25",
        "location": "Monaco",
        "coordinates": {
            "lat": 43.7347,
            "lon": 7.4206
        },
        "description": {
            "country": "Monaco",
            "location": "Monte Carlo",
            "opened": 1929,
            "usedSince": 1950,
            "length": "3.337 km",
            "direction": "clockwise",
            "lapRecord": "1:12.909 (Lewis Hamilton, Mercedes, 2019)"
        },
        "sprint": false,
        "sessions": {
        "practice1": "2025-05-23T11:30:00Z",
        "practice2": "2025-05-23T15:00:00Z",
        "practice3": "2025-05-24T10:30:00Z",
        "quali": "2025-05-24T14:00:00Z",
        "race": "2025-05-25T13:00:00Z"
}
    },
    {
        "round": 9,
        "name": "Spain",
        "start": "2025-05-30",
        "end": "2025-06-01",
        "location": "Barcelona",
        "coordinates": {
            "lat": 41.5701,
            "lon": 2.2611
        },
        "description": {
            "country": "Spain",
            "location": "Montmeló, Catalonia",
            "opened": 1991,
            "usedSince": 1991,
            "length": "4.675 km",
            "direction": "clockwise",
            "lapRecord": "1:16.330 (Max Verstappen, Red Bull, 2023)"
        },
        "sprint": false,
        "sessions": {
        "practice1": "2025-05-30T11:30:00Z",
        "practice2": "2025-05-30T15:00:00Z",
        "practice3": "2025-05-31T10:30:00Z",
        "quali": "2025-05-31T14:00:00Z",
        "race": "2025-06-01T13:00:00Z"
}
    },
    {
        "round": 10,
        "name": "Canada",
        "start": "2025-06-13",
        "end": "2025-06-15",
        "location": "Montreal",
        "coordinates": {
            "lat": 45.5000,
            "lon": -73.5228
        },
        "description": {
            "country": "Canada",
            "location": "Montreal, Quebec",
            "opened": 1978,
            "usedSince": 1978,
            "length": "4.361 km",
            "direction": "clockwise",
            "lapRecord": "1:13.078 (Valtteri Bottas, Mercedes, 2019)"
        },
        "sprint": false,
        "sessions": {
        "practice1": "2025-06-13T23:30:00Z",
        "practice2": "2025-06-14T03:00:00Z",
        "practice3": "2025-06-14T22:30:00Z",
        "quali": "2025-06-15T02:00:00Z",
        "race": "2025-06-15T20:00:00Z"
}
    },
    {
        "round": 11,
        "name": "Austria",
        "start": "2025-06-27",
        "end": "2025-06-29",
        "location": "Spielberg",
        "coordinates": {
            "lat": 47.2197,
            "lon": 14.7646
        },
        "description": {
            "country": "Austria",
            "location": "Spielberg, Styria",
            "opened": 1969,
            "usedSince": 1970,
            "length": "4.318 km",
            "direction": "clockwise",
            "lapRecord": "1:05.619 (Carlos Sainz, Ferrari, 2020)"
        },
        "sprint": false,
        "sessions": {
        "practice1": "2025-06-27T11:30:00Z",
        "practice2": "2025-06-27T15:00:00Z",
        "practice3": "2025-06-28T10:30:00Z",
        "quali": "2025-06-28T14:00:00Z",
        "race": "2025-06-29T13:00:00Z"
}
    },
    {
        "round": 12,
        "name": "United Kingdom",
        "start": "2025-07-04",
        "end": "2025-07-06",
        "location": "Silverstone",
        "coordinates": {
            "lat": 52.0786,
            "lon": -1.0169
        },
        "description": {
            "country": "United Kingdom",
            "location": "Northamptonshire",
            "opened": 1948,
            "usedSince": 1950,
            "length": "5.891 km",
            "direction": "clockwise",
            "lapRecord": "1:27.097 (Max Verstappen, Red Bull, 2020)"
        },
        "sprint": false,
        "sessions": {
        "practice1": "2025-07-04T12:30:00Z",
        "practice2": "2025-07-04T16:00:00Z",
        "practice3": "2025-07-05T11:30:00Z",
        "quali": "2025-07-05T15:00:00Z",
        "race": "2025-07-06T15:00:00Z"
}
    },
    {
        "round": 13,
        "name": "Belgium",
        "start": "2025-07-25",
        "end": "2025-07-27",
        "location": "Spa-Francorchamps",
        "coordinates": {
            "lat": 50.4372,
            "lon": 5.9714
        },
        "description": {
            "country": "Belgium",
            "location": "Stavelot, Wallonia",
            "opened": 1921,
            "usedSince": 1950,
            "length": "7.004 km",
            "direction": "clockwise",
            "lapRecord": "1:46.286 (Lewis Hamilton, Mercedes, 2020)"
        },
        "sprint": true,
        "sessions": {
        "practice1": "2025-07-25T10:30:00Z",
        "sprintQuali": "2025-07-25T14:30:00Z",
        "sprint": "2025-07-26T10:00:00Z",
        "quali": "2025-07-26T14:00:00Z",
        "race": "2025-07-27T13:00:00Z"
}
    },
    {
        "round": 14,
        "name": "Hungary",
        "start": "2025-08-01",
        "end": "2025-08-03",
        "location": "Hungaroring",
        "coordinates": {
            "lat": 47.5829,
            "lon": 19.2486
        },
        "description": {
            "country": "Hungary",
            "location": "Mogyoród, near Budapest",
            "opened": 1986,
            "usedSince": 1986,
            "length": "4.381 km",
            "direction": "clockwise",
            "lapRecord": "1:16.627 (Lewis Hamilton, Mercedes, 2020)"
        },
        "sprint": false,
        "sessions": {
        "practice1": "2025-08-01T11:30:00Z",
        "practice2": "2025-08-01T15:00:00Z",
        "practice3": "2025-08-02T10:30:00Z",
        "quali": "2025-08-02T14:00:00Z",
        "race": "2025-08-03T13:00:00Z"
}
    },
    {
        "round": 15,
        "name": "Netherlands",
        "start": "2025-08-29",
        "end": "2025-08-31",
        "location": "Zandvoort",
        "coordinates": {
            "lat": 52.3888,
            "lon": 4.5409
        },
        "description": {
            "country": "Netherlands",
            "location": "Zandvoort, North Holland",
            "opened": 1948,
            "usedSince": 2021,
            "length": "4.259 km",
            "direction": "clockwise",
            "lapRecord": "1:11.097 (Lewis Hamilton, Mercedes, 2021)"
        },
        "sprint": false,
        "sessions": {
        "practice1": "2025-08-29T10:30:00Z",
        "practice2": "2025-08-29T14:00:00Z",
        "practice3": "2025-08-30T09:30:00Z",
        "quali": "2025-08-30T13:00:00Z",
        "race": "2025-08-31T13:00:00Z"
}
    },
    {
        "round": 16,
        "name": "Italy",
        "start": "2025-09-05",
        "end": "2025-09-07",
        "location": "Monza",
        "coordinates": {
            "lat": 45.6156,
            "lon": 9.2811
        },
        "description": {
            "country": "Italy",
            "location": "Monza, Lombardy",
            "opened": 1922,
            "usedSince": 1950,
            "length": "5.793 km",
            "direction": "clockwise",
            "lapRecord": "1:21.046 (Rubens Barrichello, Ferrari, 2004)"
        },
        "sprint": false,"sessions": {
        "practice1": "2025-09-05T11:30:00Z",
        "practice2": "2025-09-05T15:00:00Z",
        "practice3": "2025-09-06T10:30:00Z",
        "quali": "2025-09-06T14:00:00Z",
        "race": "2025-09-07T13:00:00Z"
}
    },
    {
        "round": 17,
        "name": "Azerbaijan",
        "start": "2025-09-19",
        "end": "2025-09-21",
        "location": "Baku",
        "coordinates": {
            "lat": 40.3725,
            "lon": 49.8533
        },
        "description": {
            "country": "Azerbaijan",
            "location": "Baku",
            "opened": 2016,
            "usedSince": 2017,
            "length": "6.003 km",
            "direction": "counterclockwise",
            "lapRecord": "1:43.009 (Charles Leclerc, Ferrari, 2019)"
        },
        "sprint": false,
        "sessions": {
        "practice1": "2025-09-19T06:30:00Z",
        "practice2": "2025-09-19T10:00:00Z",
        "practice3": "2025-09-20T06:30:00Z",
        "quali": "2025-09-20T10:00:00Z",
        "race": "2025-09-21T09:00:00Z"
}
    },
    {
        "round": 18,
        "name": "Singapore",
        "start": "2025-10-03",
        "end": "2025-10-05",
        "location": "Singapore",
        "coordinates": {
            "lat": 1.2914,
            "lon": 103.8640
        },
        "description": {
            "country": "Singapore",
            "location": "Marina Bay",
            "opened": 2008,
            "usedSince": 2008,
            "length": "5.063 km",
            "direction": "counterclockwise",
            "lapRecord": "1:41.905 (Kevin Magnussen, Haas, 2018)"
        },
        "sprint": false,
        "sessions": {
        "practice1": "2025-10-03T03:30:00Z",
        "practice2": "2025-10-03T07:00:00Z",
        "practice3": "2025-10-04T03:30:00Z",
        "quali": "2025-10-04T07:00:00Z",
        "race": "2025-10-05T06:00:00Z"
}
    },
    {
        "round": 19,
        "name": "United States",
        "start": "2025-10-17",
        "end": "2025-10-19",
        "location": "Austin",
        "coordinates": {
            "lat": 30.1328,
            "lon": -97.6411
        },
        "description": {
            "country": "United States",
            "location": "Austin, Texas",
            "opened": 2012,
            "usedSince": 2012,
            "length": "5.513 km",
            "direction": "counterclockwise",
            "lapRecord": "1:36.169 (Charles Leclerc, Ferrari, 2019)"
        },
        "sprint": true,
        "sessions": {
        "practice1": "2025-10-17T23:30:00Z",
        "sprintQuali": "2025-10-18T03:30:00Z",
        "sprint": "2025-10-18T23:00:00Z",
        "quali": "2025-10-19T03:00:00Z",
        "race": "2025-10-19T23:00:00Z"
}
    },
    {
        "round": 20,
        "name": "Mexico",
        "start": "2025-10-24",
        "end": "2025-10-26",
        "location": "Mexico City",
        "coordinates": {
            "lat": 19.4042,
            "lon": -99.0907
        },
        "description": {
            "country": "Mexico",
            "location": "Mexico City",
            "opened": 1962,
            "usedSince": 2015,
            "length": "4.304 km",
            "direction": "clockwise",
            "lapRecord": "1:17.774 (Valtteri Bottas, Mercedes, 2021)"
        },
        "sprint": false,
        "sessions": {
        "practice1": "2025-10-24T01:30:00Z",
        "practice2": "2025-10-25T05:00:00Z",
        "practice3": "2025-10-25T23:30:00Z",
        "quali": "2025-10-26T03:00:00Z",
        "race": "2025-10-26T23:00:00Z"
}
    },
    {
        "round": 21,
        "name": "Brazil",
        "start": "2025-11-07",
        "end": "2025-11-09",
        "location": "São Paulo",
        "coordinates": {
            "lat": -23.7036,
            "lon": -46.6997
        },
        "description": {
            "country": "Brazil",
            "location": "São Paulo",
            "opened": 1940,
            "usedSince": 1990,
            "length": "4.309 km",
            "direction": "counterclockwise",
            "lapRecord": "1:10.540 (Valtteri Bottas, Mercedes, 2018)"
        },
        "sprint": true,
        "sessions": {
        "practice1": "2025-11-07T18:30:00Z",
        "sprintQuali": "2025-11-07T22:30:00Z",
        "sprint": "2025-11-08T18:00:00Z",
        "quali": "2025-11-08T22:00:00Z",
        "race": "2025-11-09T20:00:00Z"
}
    },
    {
        "round": 22,
        "name": "Las Vegas",
        "start": "2025-11-20",
        "end": "2025-11-22",
        "location": "Las Vegas",
        "coordinates": {
            "lat": 36.1162,
            "lon": -115.1745
        },
        "description": {
            "country": "United States",
            "location": "Las Vegas, Nevada",
            "opened": 2023,
            "usedSince": 2023,
            "length": "6.201 km",
            "direction": "counterclockwise",
            "lapRecord": "1:35.490 (George Russell, Mercedes, 2023)"
        },
        "sprint": false,
        "sessions": {
        "practice1": "2025-11-21T09:30:00Z",
        "practice2": "2025-11-21T13:00:00Z",
        "practice3": "2025-11-22T09:30:00Z",
        "quali": "2025-11-22T13:00:00Z",
        "race": "2025-11-23T13:00:00Z"
}
    },
    {
        "round": 23,
        "name": "Qatar",
        "start": "2025-11-28",
        "end": "2025-11-30",
        "location": "Losail",
        "coordinates": {
            "lat": 25.4900,
            "lon": 51.4542
        },
        "description": {
            "country": "Qatar",
            "location": "Losail",
            "opened": 2004,
            "usedSince": 2021,
            "length": "5.380 km",
            "direction": "clockwise",
            "lapRecord": "1:24.319 (Max Verstappen, Red Bull, 2021)"
        },
        "sprint": true,
        "sessions": {
        "practice1": "2025-11-28T11:30:00Z",
        "sprintQuali": "2025-11-28T15:30:00Z",
        "sprint": "2025-11-29T12:00:00Z",
        "quali": "2025-11-29T16:00:00Z",
        "race": "2025-11-30T14:00:00Z"
}
    },
    {
        "round": 24,
        "name": "Abu Dhabi",
        "start": "2025-12-05",
        "end": "2025-12-07",
        "location": "Yas Marina",
        "coordinates": {
            "lat": 24.4672,
            "lon": 54.6031
        },
        "description": {
            "country": "United Arab Emirates",
            "location": "Abu Dhabi",
            "opened": 2009,
            "usedSince": 2009,
            "length": "5.281 km",
            "direction": "counterclockwise",
            "lapRecord": "1:26.103 (Max Verstappen, Red Bull, 2021)"
        },
        "sprint": false,
        "sessions": {
        "practice1": "2025-12-05T06:30:00Z",
        "practice2": "2025-12-05T10:00:00Z",
        "practice3": "2025-12-06T07:30:00Z",
        "quali": "2025-12-06T11:00:00Z",
        "race": "2025-12-07T10:00:00Z"
}
    }
],
"driversStandings": [
    {
        "position": 1,
        "driver": "Lando Norris",
        "team": "McLaren",
        "points": 62,
        "nationality": "British",
        "driverNumber": 4,
        "dateOfBirth": "1999-11-13",
        "wins": 5,
        "podiums": 29,
        "debut": "2019 Australian Grand Prix",
        "bio": "Lando Norris is a British racing driver known for his speed and consistency 🏎️💨. Rising through the ranks of McLaren's junior program, he made his F1 debut in 2019. Known for his cheerful personality off the track 😄 and fierce competitiveness on it 🔥, Norris has quickly become a fan favorite and a strong contender for the championship 🏆.",
        "races": 132,
        "bestGridPosition": "1",
        "bestRaceFinish": "1",
        "wdcWins": 0,
        "careerYears": 8,
        "careerEarnings": 45000000
    },
    {
        "position": 2,
        "driver": "Max Verstappen",
        "team": "Red Bull Racing",
        "points": 61,
        "nationality": "Dutch",
        "driverNumber": 1,
        "dateOfBirth": "1997-09-30",
        "wins": 64,
        "podiums": 113,
        "debut": "2015 Australian Grand Prix",
        "bio": "Max Verstappen, a Dutch prodigy 🇳🇱, became the youngest F1 race winner in 2016 with Red Bull 🏁. Known for his aggressive driving style 🔥 and incredible racecraft, Verstappen has dominated recent seasons, securing multiple world championships 🏆 and establishing himself as one of F1's all-time greats 🌟.",
        "races": 213,
        "bestGridPosition": "1",
        "bestRaceFinish": "1",
        "wdcWins": 4,
        "careerYears": 12,
        "careerEarnings": 150000000
    },
    {
        "position": 3,
        "driver": "Oscar Piastri",
        "team": "McLaren",
        "points": 49,
        "nationality": "Australian",
        "driverNumber": 81,
        "dateOfBirth": "2001-04-06",
        "wins": 3,
        "podiums": 12,
        "debut": "2023 Bahrain Grand Prix",
        "bio": "Oscar Piastri, a young Australian talent 🇦🇺, joined McLaren in 2023 after a controversial transfer saga 😬. With a stellar junior career, including winning the F2 championship 🏅, Piastri has shown immense potential in F1, often matching or outperforming his more experienced teammate, Lando Norris 🚀.",
        "races": 50,
        "bestGridPosition": "1",
        "bestRaceFinish": "1",
        "wdcWins": 0,
        "careerYears": 3,
        "careerEarnings": 12000000
    },
    {
        "position": 4,
        "driver": "George Russell",
        "team": "Mercedes",
        "points": 45,
        "nationality": "British",
        "driverNumber": 63,
        "dateOfBirth": "1998-02-15",
        "wins": 3,
        "podiums": 17,
        "debut": "2019 Australian Grand Prix",
        "bio": "George Russell made a name for himself with Williams before moving to Mercedes in 2022 🌟. Known for his qualifying prowess ⏱️ and ability to extract the maximum from the car, Russell is seen as a future world champion 🏆, often delivering strong performances under pressure 💪.",
        "races": 132,
        "bestGridPosition": "1",
        "bestRaceFinish": "1",
        "wdcWins": 0,
        "careerYears": 8,
        "careerEarnings": 30000000
    },
    {
        "position": 5,
        "driver": "Kimi Antonelli",
        "team": "Mercedes",
        "points": 30,
        "nationality": "Italian",
        "driverNumber": 12,
        "dateOfBirth": "2006-08-25",
        "wins": 0,
        "podiums": 0,
        "debut": "2025 Australian Grand Prix",
        "bio": "Kimi Antonelli is a highly-rated Italian rookie 🇮🇹 who joined Mercedes in 2025. Touted as a future star 🌟, Antonelli skipped several junior categories to fast-track his way to F1 🚀, impressing with his maturity and speed in his debut season 😊.",
        "races": 3,
        "bestGridPosition": "6",
        "bestRaceFinish": "4",
        "wdcWins": 0,
        "careerYears": 1,
        "careerEarnings": 1000000
    },
    {
        "position": 6,
        "driver": "Charles Leclerc",
        "team": "Ferrari",
        "points": 20,
        "nationality": "Monegasque",
        "driverNumber": 16,
        "dateOfBirth": "1997-10-16",
        "wins": 8,
        "podiums": 43,
        "debut": "2018 Australian Grand Prix",
        "bio": "Charles Leclerc, a Monegasque driver 🇲🇨, joined Ferrari in 2019 and quickly became a fan favorite ❤️. Known for his raw speed 🏎️ and emotional connection with the Tifosi 🇮🇹, Leclerc is seen as Ferrari's hope for a future championship 🏆.",
        "races": 151,
        "bestGridPosition": "1",
        "bestRaceFinish": "1",
        "wdcWins": 0,
        "careerYears": 10,
        "careerEarnings": 50000000
    },
    {
        "position": 7,
        "driver": "Alex Albon",
        "team": "Williams",
        "points": 18,
        "nationality": "Thai",
        "driverNumber": 23,
        "dateOfBirth": "1996-03-23",
        "wins": 0,
        "podiums": 2,
        "debut": "2019 Australian Grand Prix",
        "bio": "Alex Albon, a Thai-British driver 🇹🇭🇬🇧, has been a consistent performer for Williams since his return to F1 in 2023. Known for his defensive driving 🛡️ and ability to score points in a midfield car, Albon is a key asset for his team 💪.",
        "races": 108,
        "bestGridPosition": "4",
        "bestRaceFinish": "3",
        "wdcWins": 0,
        "careerYears": 6,
        "careerEarnings": 20000000
    },
    {
        "position": 8,
        "driver": "Lewis Hamilton",
        "team": "Ferrari",
        "points": 15,
        "nationality": "British",
        "driverNumber": 44,
        "dateOfBirth": "1985-01-07",
        "wins": 105,
        "podiums": 202,
        "debut": "2007 Australian Grand Prix",
        "bio": "Lewis Hamilton, a seven-time world champion 🏆🏆🏆🏆🏆🏆🏆, joined Ferrari in 2025 after a legendary tenure with Mercedes. Known for his activism ✊ and record-breaking career 🌟, Hamilton aims to end his F1 journey with another title at the iconic Italian team 🇮🇹🔴.",
        "races": 360,
        "bestGridPosition": "1",
        "bestRaceFinish": "1",
        "wdcWins": 7,
        "careerYears": 19,
        "careerEarnings": 500000000
    },
    {
        "position": 9,
        "driver": "Esteban Ocon",
        "team": "Alpine",
        "points": 10,
        "nationality": "French",
        "driverNumber": 31,
        "dateOfBirth": "1996-09-17",
        "wins": 1,
        "podiums": 4,
        "debut": "2016 Belgian Grand Prix",
        "bio": "Esteban Ocon, a French driver 🇫🇷, races for Alpine. Known for his work ethic 💼 and consistency, Ocon has been a steady performer in the midfield, with his first F1 win coming in Hungary in 2021 🏅.",
        "races": 160,
        "bestGridPosition": "3",
        "bestRaceFinish": "1",
        "wdcWins": 0,
        "careerYears": 10,
        "careerEarnings": 20000000
    },
    {
        "position": 10,
        "driver": "Lance Stroll",
        "team": "Aston Martin",
        "points": 10,
        "nationality": "Canadian",
        "driverNumber": 18,
        "dateOfBirth": "1998-10-29",
        "wins": 0,
        "podiums": 3,
        "debut": "2017 Australian Grand Prix",
        "bio": "Lance Stroll, a Canadian driver 🇨🇦, races for Aston Martin, a team owned by his father, Lawrence Stroll. While often criticized for his seat due to family ties 😕, Stroll has shown flashes of brilliance, particularly in wet conditions 🌧️.",
        "races": 170,
        "bestGridPosition": "1",
        "bestRaceFinish": "3",
        "wdcWins": 0,
        "careerYears": 9,
        "careerEarnings": 25000000
    },
    {
        "position": 11,
        "driver": "Nico Hulkenberg",
        "team": "Haas",
        "points": 6,
        "nationality": "German",
        "driverNumber": 27,
        "dateOfBirth": "1987-08-19",
        "wins": 0,
        "podiums": 0,
        "debut": "2010 Bahrain Grand Prix",
        "bio": "Nico Hulkenberg, a veteran German driver 🇩🇪, is known for his consistency and qualifying speed ⏱️. Despite never achieving a podium in F1 😢, Hulkenberg remains a respected figure in the paddock, often extracting the maximum from the Haas car 💪.",
        "races": 231,
        "bestGridPosition": "1",
        "bestRaceFinish": "4",
        "wdcWins": 0,
        "careerYears": 15,
        "careerEarnings": 35000000
    },
    {
        "position": 12,
        "driver": "Oliver Bearman",
        "team": "Haas",
        "points": 5,
        "nationality": "British",
        "driverNumber": 87,
        "dateOfBirth": "2005-05-08",
        "wins": 0,
        "podiums": 0,
        "debut": "2025 Australian Grand Prix",
        "bio": "Oliver Bearman, a British rookie 🇬🇧, joined Haas in 2025 after impressing in F2. A Ferrari junior driver 🔴, Bearman is seen as a future talent 🌟, with his debut season showing promise 🚀.",
        "races": 7,
        "bestGridPosition": "10",
        "bestRaceFinish": "7",
        "wdcWins": 0,
        "careerYears": 1,
        "careerEarnings": 800000
    },
    {
        "position": 13,
        "driver": "Isack Hadjar",
        "team": "RB",
        "points": 4,
        "nationality": "French",
        "driverNumber": 6,
        "dateOfBirth": "2004-09-28",
        "wins": 0,
        "podiums": 0,
        "debut": "2025 Australian Grand Prix",
        "bio": "Isack Hadjar, a French rookie 🇫🇷, joined RB in 2025. A Red Bull junior driver 🔵, Hadjar impressed in F2 and is looking to make his mark in F1 with his aggressive driving style 🔥.",
        "races": 3,
        "bestGridPosition": "7",
        "bestRaceFinish": "8",
        "wdcWins": 0,
        "careerYears": 1,
        "careerEarnings": 700000
    },
    {
        "position": 14,
        "driver": "Yuki Tsunoda",
        "team": "Red Bull Racing",
        "points": 3,
        "nationality": "Japanese",
        "driverNumber": 22,
        "dateOfBirth": "2000-05-11",
        "wins": 0,
        "podiums": 0,
        "debut": "2021 Bahrain Grand Prix",
        "bio": "Yuki Tsunoda, a Japanese driver 🇯🇵, races for RB. Known for his aggressive driving 🔥 and fiery radio messages 📡, Tsunoda has matured into a consistent points-scorer for his team 💪.",
        "races": 91,
        "bestGridPosition": "5",
        "bestRaceFinish": "4",
        "wdcWins": 0,
        "careerYears": 5,
        "careerEarnings": 10000000
    },
    {
        "position": 15,
        "driver": "Carlos Sainz",
        "team": "Williams",
        "points": 1,
        "nationality": "Spanish",
        "driverNumber": 55,
        "dateOfBirth": "1994-09-01",
        "wins": 4,
        "podiums": 27,
        "debut": "2015 Australian Grand Prix",
        "bio": "Carlos Sainz, a Spanish driver 🇪🇸, moved to Williams in 2025 after stints with Ferrari and McLaren. Known for his smooth driving style 🏎️ and consistency, Sainz is a reliable performer in the midfield 💪.",
        "races": 210,
        "bestGridPosition": "1",
        "bestRaceFinish": "1",
        "wdcWins": 0,
        "careerYears": 11,
        "careerEarnings": 40000000
    },
    {
        "position": 16,
        "driver": "Pierre Gasly",
        "team": "Alpine",
        "points": 0,
        "nationality": "French",
        "driverNumber": 10,
        "dateOfBirth": "1996-02-07",
        "wins": 1,
        "podiums": 5,
        "debut": "2017 Malaysian Grand Prix",
        "bio": "Pierre Gasly, a French driver 🇫🇷, races for Alpine. Known for his speed 🏎️ and resilience 💪, Gasly scored his first F1 win at Monza in 2020 with AlphaTauri 🏆, and continues to be a strong midfield contender 🔥.",
        "races": 151,
        "bestGridPosition": "2",
        "bestRaceFinish": "1",
        "wdcWins": 0,
        "careerYears": 9,
        "careerEarnings": 25000000
    },
    {
        "position": 17,
        "driver": "Fernando Alonso",
        "team": "Aston Martin",
        "points": 0,
        "nationality": "Spanish",
        "driverNumber": 14,
        "dateOfBirth": "1981-07-29",
        "wins": 32,
        "podiums": 106,
        "debut": "2001 Australian Grand Prix",
        "bio": "Fernando Alonso, a two-time world champion 🏆🏆, continues to race for Aston Martin in 2025. Known for his experience 🧠 and relentless drive 💪, Alonso remains a formidable competitor despite being the oldest driver on the grid 👴.",
        "races": 405,
        "bestGridPosition": "1",
        "bestRaceFinish": "1",
        "wdcWins": 2,
        "careerYears": 22,
        "careerEarnings": 250000000
    },
    {
        "position": 18,
        "driver": "Liam Lawson",
        "team": "RB",
        "points": 0,
        "nationality": "New Zealander",
        "driverNumber": 30,
        "dateOfBirth": "2002-02-11",
        "wins": 0,
        "podiums": 0,
        "debut": "2023 Dutch Grand Prix",
        "bio": "Liam Lawson, a New Zealander 🇳🇿, joined Red Bull Racing in 2025 after impressing as a reserve driver. Known for his versatility 🌟 and speed 🏎️, Lawson is a promising talent in the Red Bull lineup 🚀.",
        "races": 15,
        "bestGridPosition": "5",
        "bestRaceFinish": "9",
        "wdcWins": 0,
        "careerYears": 4,
        "careerEarnings": 3000000
    },
    {
        "position": 19,
        "driver": "Jack Doohan",
        "team": "Alpine",
        "points": 0,
        "nationality": "Australian",
        "driverNumber": 7,
        "dateOfBirth": "2003-01-20",
        "wins": 0,
        "podiums": 0,
        "debut": "2025 Australian Grand Prix",
        "bio": "Jack Doohan, an Australian rookie 🇦🇺, joined Alpine in 2025. A former F2 frontrunner 🏅, Doohan is known for his technical feedback 📝 and consistency, aiming to make an impact in his debut season 🚀.",
        "races": 5,
        "bestGridPosition": "14",
        "bestRaceFinish": "13",
        "wdcWins": 0,
        "careerYears": 1,
        "careerEarnings": 600000
    },
    {
        "position": 20,
        "driver": "Gabriel Bortoleto",
        "team": "Sauber",
        "points": 0,
        "nationality": "Brazilian",
        "driverNumber": 5,
        "dateOfBirth": "2004-10-14",
        "wins": 0,
        "podiums": 0,
        "debut": "2025 Australian Grand Prix",
        "bio": "Gabriel Bortoleto, a Brazilian rookie 🇧🇷, joined Sauber in 2025. A former F3 champion 🏆, Bortoleto is part of McLaren's junior program and is looking to establish himself in F1 🌟.",
        "races": 4,
        "bestGridPosition": "15",
        "bestRaceFinish": "14",
        "wdcWins": 0,
        "careerYears": 1,
        "careerEarnings": 500000
    }
],
"constructorsStandings": [
    {
        "position": 1,
        "team": "McLaren",
        "points": 111,
        "seasons": 60,
        "racesCompleted": 974,
        "polePositions": 166,
        "podiums": 527,
        "raceWins": 191,
        "wccWins": 9,
        "wdcWins": 12,
        "nationality": "British",
        "base": "Woking, Surrey, UK",
        "powerUnit": "Mercedes",
        "drivers": ["Lando Norris", "Oscar Piastri"],
        "bio": "McLaren was founded in 1963 by Bruce McLaren and has since become one of the most successful teams in Formula 1 history. Based in Woking, Surrey, McLaren is known for its engineering excellence and has produced champions like Ayrton Senna and Lewis Hamilton."
    },
    {
        "position": 2,
        "team": "Mercedes",
        "points": 75,
        "seasons": 18,
        "racesCompleted": 321,
        "polePositions": 141,
        "podiums": 300,
        "raceWins": 129,
        "wccWins": 8,
        "wdcWins": 9,
        "nationality": "German",
        "base": "Brackley, UK",
        "powerUnit": "Mercedes",
        "drivers": ["George Russell", "Kimi Antonelli"],
        "bio": "Mercedes returned to Formula 1 as a constructor in 2010 and quickly became a dominant force, especially during the hybrid era. Based in Brackley, the team has been home to legends like Lewis Hamilton and continues to push the boundaries of technology."
    },
    {
        "position": 3,
        "team": "Red Bull Racing",
        "points": 61,
        "seasons": 21,
        "racesCompleted": 397,
        "polePositions": 103,
        "podiums": 283,
        "raceWins": 122,
        "wccWins": 6,
        "wdcWins": 8,
        "nationality": "Austrian",
        "base": "Milton Keynes, UK",
        "powerUnit": "Honda RBPT",
        "drivers": ["Max Verstappen", "Yuki Tsunoda"],
        "bio": "Red Bull Racing, founded in 2005, is based in Milton Keynes and has been a powerhouse in F1, especially with drivers like Sebastian Vettel and Max Verstappen. Known for its aggressive strategies and innovative designs."
    },
    {
        "position": 4,
        "team": "Ferrari",
        "points": 35,
        "seasons": 76,
        "racesCompleted": 1102,
        "polePositions": 253,
        "podiums": 829,
        "raceWins": 248,
        "wccWins": 16,
        "wdcWins": 15,
        "nationality": "Italian",
        "base": "Maranello, Italy",
        "powerUnit": "Ferrari",
        "drivers": ["Charles Leclerc", "Lewis Hamilton"],
        "bio": "Ferrari, founded in 1950, is the most iconic team in F1 history. Based in Maranello, Italy, Ferrari has a passionate fanbase, the Tifosi, and a legacy of champions like Michael Schumacher."
    },
    {
        "position": 5,
        "team": "Williams",
        "points": 19,
        "seasons": 50,
        "racesCompleted": 855,
        "polePositions": 128,
        "podiums": 313,
        "raceWins": 114,
        "wccWins": 9,
        "wdcWins": 7,
        "nationality": "British",
        "base": "Grove, UK",
        "powerUnit": "Mercedes",
        "drivers": ["Alex Albon", "Carlos Sainz"],
        "bio": "Williams, founded in 1977 by Frank Williams, is one of the most storied teams in F1. Based in Grove, the team dominated in the 1980s and 1990s but has struggled in recent years, aiming for a comeback."
    },
    {
        "position": 6,
        "team": "Haas",
        "points": 15,
        "seasons": 10,
        "racesCompleted": 194,
        "polePositions": 1,
        "podiums": 0,
        "raceWins": 0,
        "wccWins": 0,
        "wdcWins": 0,
        "nationality": "American",
        "base": "Kannapolis, USA",
        "powerUnit": "Ferrari",
        "drivers": ["Oliver Bearman", "Esteban Ocon"],
        "bio": "Haas, an American team founded in 2016, is based in Kannapolis, North Carolina, with operations in Banbury, UK. Known for its partnership with Ferrari, Haas focuses on efficiency in the midfield."
    },
    {
        "position": 7,
        "team": "Aston Martin",
        "points": 10,
        "seasons": 7,
        "racesCompleted": 99,
        "polePositions": 0,
        "podiums": 9,
        "raceWins": 0,
        "wccWins": 0,
        "wdcWins": 0,
        "nationality": "British",
        "base": "Silverstone, UK",
        "powerUnit": "Mercedes",
        "drivers": ["Fernando Alonso", "Lance Stroll"],
        "bio": "Aston Martin returned to F1 in 2021, with its base in Silverstone. Backed by Lawrence Stroll, the team aims to become a championship contender with drivers like Fernando Alonso."
    },
    {
        "position": 8,
        "team": "RB",
        "points": 7,
        "seasons": 1,
        "racesCompleted": 4,
        "polePositions": 0,
        "podiums": 0,
        "raceWins": 0,
        "wccWins": 0,
        "wdcWins": 0,
        "nationality": "Italian",
        "base": "Faenza, Italy",
        "powerUnit": "Honda RBPT",
        "drivers": ["Isack Hadjar", "Liam Lawson"],
        "bio": "RB, formerly AlphaTauri, is Red Bull's sister team, based in Faenza, Italy. Since 2020, it has served as a development team for Red Bull's young drivers like Yuki Tsunoda."
    },
    {
        "position": 9,
        "team": "Sauber",
        "points": 6,
        "seasons": 21,
        "racesCompleted": 375,
        "polePositions": 0,
        "podiums": 10,
        "raceWins": 0,
        "wccWins": 0,
        "wdcWins": 0,
        "nationality": "Swiss",
        "base": "Hinwil, Switzerland",
        "powerUnit": "Ferrari",
        "drivers": ["Nico Hulkenberg", "Gabriel Bortoleto"],
        "bio": "Sauber, based in Hinwil, Switzerland, has been in F1 since 1993. Set to become Audi in 2026, the team has a history of nurturing talent like Kimi Räikkönen."
    },
    {
        "position": 10,
        "team": "Alpine",
        "points": 0,
        "seasons": 4,
        "racesCompleted": 94,
        "polePositions": 0,
        "podiums": 6,
        "raceWins": 1,
        "wccWins": 0,
        "wdcWins": 0,
        "nationality": "French",
        "base": "Enstone, UK",
        "powerUnit": "Renault",
        "drivers": ["Pierre Gasly", "Jack Doohan"],
        "bio": "Alpine, the rebranded Renault team, joined F1 in 2021. Based in Enstone, UK, and Viry-Châtillon, France, Alpine aims to bring French flair to the grid with drivers like Esteban Ocon."
    }
]
}